[
    {
        "formatted_address": "1150 S Beach Blvd, Waveland, MS 39576, United States",
        "geometry": {
            "location": {
                "lat": 30.2605604,
                "lng": -89.405305
            },
            "viewport": {
                "northeast": {
                    "lat": 30.26189457989272,
                    "lng": -89.40394902010728
                },
                "southwest": {
                    "lat": 30.25919492010727,
                    "lng": -89.40664867989273
                }
            }
        },
        "name": "Buccaneer State Park",
        "opening_hours": {
            "open_now": false
        },
        "rating": 4.1
    },
    {
        "formatted_address": "366 Ft Adams Pond Rd, Woodville, MS 39669, United States",
        "geometry": {
            "location": {
                "lat": 31.0718537,
                "lng": -91.5115036
            },
            "viewport": {
                "northeast": {
                    "lat": 31.07326127989272,
                    "lng": -91.51012387010728
                },
                "southwest": {
                    "lat": 31.07056162010727,
                    "lng": -91.51282352989273
                }
            }
        },
        "name": "Clark Creek Natural Area",
        "opening_hours": {
            "open_now": false
        },
        "rating": 4.7
    },
    {
        "formatted_address": "386 Clarkco Road, Clark County Rd, Quitman, MS 39355, United States",
        "geometry": {
            "location": {
                "lat": 32.0977144,
                "lng": -88.6897785
            },
            "viewport": {
                "northeast": {
                    "lat": 32.09946502989273,
                    "lng": -88.68842057010728
                },
                "southwest": {
                    "lat": 32.09676537010728,
                    "lng": -88.69112022989272
                }
            }
        },
        "name": "Clarkco State Park",
        "opening_hours": {
            "open_now": false
        },
        "rating": 4.6
    },
    {
        "formatted_address": "1999 Co Rd 145, Greenwood, MS 38930, United States",
        "geometry": {
            "location": {
                "lat": 33.5262875,
                "lng": -90.24715760000001
            },
            "viewport": {
                "northeast": {
                    "lat": 33.52756602989272,
                    "lng": -90.2455463201073
                },
                "southwest": {
                    "lat": 33.52486637010728,
                    "lng": -90.24824597989273
                }
            }
        },
        "name": "Florewood Park",
        "rating": 4.2
    },
    {
        "formatted_address": "165 Co Rd 170, Oakland, MS 38948, United States",
        "geometry": {
            "location": {
                "lat": 34.1327212,
                "lng": -89.886682
            },
            "viewport": {
                "northeast": {
                    "lat": 34.13411882989273,
                    "lng": -89.88551307010728
                },
                "southwest": {
                    "lat": 34.13141917010728,
                    "lng": -89.88821272989271
                }
            }
        },
        "name": "George P Cossar State Park",
        "rating": 4.4
    },
    {
        "formatted_address": "2104 Damascus Rd, Walnut Grove, MS 39189, United States",
        "geometry": {
            "location": {
                "lat": 32.5727565,
                "lng": -89.4063141
            },
            "viewport": {
                "northeast": {
                    "lat": 32.5736804,
                    "lng": -89.40483515
                },
                "southwest": {
                    "lat": 32.56998479999999,
                    "lng": -89.41075095000001
                }
            }
        },
        "name": "Golden Memorial State Park",
        "rating": 3.7
    },
    {
        "formatted_address": "100 St Park Rd, Rosedale, MS 38769, United States",
        "geometry": {
            "location": {
                "lat": 33.8474455,
                "lng": -91.03862690000001
            },
            "viewport": {
                "northeast": {
                    "lat": 33.84882327989272,
                    "lng": -91.03725952010728
                },
                "southwest": {
                    "lat": 33.84612362010728,
                    "lng": -91.03995917989272
                }
            }
        },
        "name": "Great River Road State Park",
        "rating": 3.7
    },
    {
        "formatted_address": "5369 State Park Rd, Durant, MS 39063, United States",
        "geometry": {
            "location": {
                "lat": 33.027346,
                "lng": -89.9203651
            },
            "viewport": {
                "northeast": {
                    "lat": 33.02868047989272,
                    "lng": -89.91900992010727
                },
                "southwest": {
                    "lat": 33.02598082010728,
                    "lng": -89.92170957989272
                }
            }
        },
        "name": "Holmes County State Park",
        "rating": 3.9
    },
    {
        "formatted_address": "3170 State Park Road, Grenada, MS 38902, United States",
        "geometry": {
            "location": {
                "lat": 33.7989717,
                "lng": -89.7356484
            },
            "viewport": {
                "northeast": {
                    "lat": 33.80043482989272,
                    "lng": -89.73438062010729
                },
                "southwest": {
                    "lat": 33.79773517010727,
                    "lng": -89.73708027989272
                }
            }
        },
        "name": "Hugh White State Park",
        "opening_hours": {
            "open_now": false
        },
        "rating": 4.2
    },
    {
        "formatted_address": "4235 State Park Rd, Sardis, MS 38666, United States",
        "geometry": {
            "location": {
                "lat": 34.4094107,
                "lng": -89.8038626
            },
            "viewport": {
                "northeast": {
                    "lat": 34.41061487989272,
                    "lng": -89.80250372010728
                },
                "southwest": {
                    "lat": 34.40791522010728,
                    "lng": -89.80520337989273
                }
            }
        },
        "name": "John W Kyle State Park",
        "opening_hours": {
            "open_now": false
        },
        "rating": 4.1
    },
    {
        "formatted_address": "613 Co Rd 321, Iuka, MS 38852, United States",
        "geometry": {
            "location": {
                "lat": 34.9309579,
                "lng": -88.1666576
            },
            "viewport": {
                "northeast": {
                    "lat": 34.93221567989271,
                    "lng": -88.16537137010728
                },
                "southwest": {
                    "lat": 34.92951602010726,
                    "lng": -88.16807102989273
                }
            }
        },
        "name": "J P Coleman State Park",
        "opening_hours": {
            "open_now": false
        },
        "rating": 4.5
    },
    {
        "formatted_address": "2573 Sunset Rd NE, Wesson, MS 39191, United States",
        "geometry": {
            "location": {
                "lat": 31.6797076,
                "lng": -90.3392243
            },
            "viewport": {
                "northeast": {
                    "lat": 31.68040027989272,
                    "lng": -90.33737492010727
                },
                "southwest": {
                    "lat": 31.67770062010728,
                    "lng": -90.34007457989271
                }
            }
        },
        "name": "Lake Lincoln State Park",
        "opening_hours": {
            "open_now": true
        },
        "rating": 4.4
    },
    {
        "formatted_address": "3319 Lake Lowndes Rd, Columbus, MS 39702, United States",
        "geometry": {
            "location": {
                "lat": 33.4356942,
                "lng": -88.30183029999999
            },
            "viewport": {
                "northeast": {
                    "lat": 33.43707692989272,
                    "lng": -88.30047882010729
                },
                "southwest": {
                    "lat": 33.43437727010728,
                    "lng": -88.30317847989272
                }
            }
        },
        "name": "Lake Lowndes State Park",
        "opening_hours": {},
        "rating": 4.6
    },
    {
        "formatted_address": "3315 Lakeland Terrace, Jackson, MS 39216, United States",
        "geometry": {
            "location": {
                "lat": 32.3268795,
                "lng": -90.1466159
            },
            "viewport": {
                "northeast": {
                    "lat": 32.32976475,
                    "lng": -90.14479447010727
                },
                "southwest": {
                    "lat": 32.32591774999998,
                    "lng": -90.1474941298927
                }
            }
        },
        "name": "LeFleur's Bluff State Park Mayes Lake",
        "opening_hours": {
            "open_now": true
        },
        "rating": 4.5
    },
    {
        "formatted_address": "635 Legion State Park Dr, Louisville, MS 39339, United States",
        "geometry": {
            "location": {
                "lat": 33.1569543,
                "lng": -89.04230109999999
            },
            "viewport": {
                "northeast": {
                    "lat": 33.16247215,
                    "lng": -89.03791405
                },
                "southwest": {
                    "lat": 33.14040075000001,
                    "lng": -89.04376344999999
                }
            }
        },
        "name": "Legion State Park",
        "opening_hours": {
            "open_now": true
        },
        "rating": 4.6
    },
    {
        "formatted_address": "1400-1402 MS-12, Hollandale, MS 38748, United States",
        "geometry": {
            "location": {
                "lat": 33.1605783,
                "lng": -90.9361122
            },
            "viewport": {
                "northeast": {
                    "lat": 33.16194422989272,
                    "lng": -90.93476237010728
                },
                "southwest": {
                    "lat": 33.15924457010728,
                    "lng": -90.93746202989271
                }
            }
        },
        "name": "Leroy Percy State Park",
        "rating": 4.4
    },
    {
        "formatted_address": "230 Wickcliff Rd, Natchez, MS 39120, United States",
        "geometry": {
            "location": {
                "lat": 31.6118267,
                "lng": -91.2307953
            },
            "viewport": {
                "northeast": {
                    "lat": 31.61316687989272,
                    "lng": -91.22948417010728
                },
                "southwest": {
                    "lat": 31.61046722010727,
                    "lng": -91.23218382989272
                }
            }
        },
        "name": "Natchez State Park",
        "rating": 4.2
    },
    {
        "formatted_address": "319 Geiger Lake Rd, Hattiesburg, MS 39401, United States",
        "geometry": {
            "location": {
                "lat": 31.1393954,
                "lng": -89.2427393
            },
            "viewport": {
                "northeast": {
                    "lat": 31.14094792989273,
                    "lng": -89.24136532010728
                },
                "southwest": {
                    "lat": 31.13824827010728,
                    "lng": -89.24406497989273
                }
            }
        },
        "name": "Paul B Johnson State Park",
        "opening_hours": {
            "open_now": false
        },
        "rating": 4.5
    },
    {
        "formatted_address": "2036 Percy Quin Dr, McComb, MS 39648, United States",
        "geometry": {
            "location": {
                "lat": 31.1901005,
                "lng": -90.5033333
            },
            "viewport": {
                "northeast": {
                    "lat": 31.19142017989272,
                    "lng": -90.50197287010728
                },
                "southwest": {
                    "lat": 31.18872052010728,
                    "lng": -90.50467252989272
                }
            }
        },
        "name": "Percy E Quin State Park",
        "opening_hours": {
            "open_now": false
        },
        "rating": 4.3
    },
    {
        "formatted_address": "2149 MS-13, Morton, MS 39117, United States",
        "geometry": {
            "location": {
                "lat": 32.3191675,
                "lng": -89.6664448
            },
            "viewport": {
                "northeast": {
                    "lat": 32.32052692989271,
                    "lng": -89.66509092010727
                },
                "southwest": {
                    "lat": 32.31782727010727,
                    "lng": -89.66779057989272
                }
            }
        },
        "name": "Roosevelt State Park",
        "opening_hours": {
            "open_now": false
        },
        "rating": 4.3
    },
    {
        "formatted_address": "3315 Lakeland Terrace, Jackson, MS 39216, United States",
        "geometry": {
            "location": {
                "lat": 32.3268795,
                "lng": -90.1466159
            },
            "viewport": {
                "northeast": {
                    "lat": 32.32976475,
                    "lng": -90.14479447010727
                },
                "southwest": {
                    "lat": 32.32591774999998,
                    "lng": -90.1474941298927
                }
            }
        },
        "name": "LeFleur's Bluff State Park Mayes Lake",
        "opening_hours": {
            "open_now": true
        },
        "rating": 4.5
    },
    {
        "formatted_address": "105 Co Rd 90, Tishomingo, MS 38873, United States",
        "geometry": {
            "location": {
                "lat": 34.6047175,
                "lng": -88.1908713
            },
            "viewport": {
                "northeast": {
                    "lat": 34.61566015,
                    "lng": -88.17728824999999
                },
                "southwest": {
                    "lat": 34.60106995,
                    "lng": -88.23162045
                }
            }
        },
        "name": "Tishomingo State Park",
        "opening_hours": {
            "open_now": true
        },
        "rating": 4.6
    },
    {
        "formatted_address": "264 Cabin Dr, Tupelo, MS 38804, United States",
        "geometry": {
            "location": {
                "lat": 34.23260560000001,
                "lng": -88.62979109999999
            },
            "viewport": {
                "northeast": {
                    "lat": 34.23396732989272,
                    "lng": -88.62842782010726
                },
                "southwest": {
                    "lat": 34.23126767010727,
                    "lng": -88.63112747989271
                }
            }
        },
        "name": "Tombigbee Lake State Park",
        "opening_hours": {
            "open_now": false
        },
        "rating": 4.5
    },
    {
        "formatted_address": "2139 Faulkner Rd, Belden, MS 38826, United States",
        "geometry": {
            "location": {
                "lat": 34.2622576,
                "lng": -88.9006634
            },
            "viewport": {
                "northeast": {
                    "lat": 34.2629988,
                    "lng": -88.89909497010727
                },
                "southwest": {
                    "lat": 34.26003400000001,
                    "lng": -88.9017946298927
                }
            }
        },
        "name": "Trace State Park",
        "rating": 4.4
    },
    {
        "formatted_address": "3946 MS-7, Holly Springs, MS 38635, United States",
        "geometry": {
            "location": {
                "lat": 34.6647507,
                "lng": -89.4605062
            },
            "viewport": {
                "northeast": {
                    "lat": 34.66610122989272,
                    "lng": -89.45915262010728
                },
                "southwest": {
                    "lat": 34.66340157010728,
                    "lng": -89.46185227989272
                }
            }
        },
        "name": "Wall Doxey State Park",
        "rating": 4.3
    }
]